{
  "source": "AutoTS Figure 8 reproduction web data",
  "cache_dir": "./results/orientation_cache",
  "orientation_ckpt": "./results/table4_orientation/AutoTS_ours_best.pth",
  "static_png": "./results/figure8/figure8_qualitative.png",
  "errors_csv": "./results/figure8/figure8_qualitative_errors.csv",
  "metadata_json": "./results/figure8/figure8_qualitative_metadata.json",
  "location_points_csv": "./results/figure8/figure8_location_points.csv",
  "map_tiles": {
    "gt_satellite": "https://mt1.google.com/vt/lyrs=s&x={x}&y={y}&z={z}",
    "estimated_road": "https://mt1.google.com/vt/lyrs=m&x={x}&y={y}&z={z}",
    "default_zoom": 18,
    "max_zoom": 20
  },
  "note": "Rendered values are recomputed from the current cache/checkpoint. Paper values are references only.",
  "rows": [
    {
      "index": 1,
      "split": "train",
      "sign_id": "3",
      "selection_reason": "paper specified sample",
      "matches_paper_sample": true,
      "category": 4,
      "paper_label": "Yield",
      "gt_direction": 1,
      "gt_direction_name": "Backward",
      "pred_direction": 1,
      "pred_direction_name": "Backward",
      "ablation": "AutoTS w/o MinCut",
      "gt_location": [
        49.008885085775056,
        8.43945640100112
      ],
      "autots": {
        "pred": [
          49.00887829202005,
          8.439497354746354
        ],
        "error_m": 3.0899193576187245,
        "outlier_indices": []
      },
      "ablation_result": {
        "pred": [
          49.00887829202005,
          8.439497354746354
        ],
        "error_m": 3.0899193576187245
      },
      "paper_reference": {
        "sign_label": "Yield",
        "gt_direction": 1,
        "gt_direction_name": "Backward",
        "pred_direction": 1,
        "pred_direction_name": "Backward",
        "autots_error_m": 2.15,
        "ablation_error_m": 3.39,
        "caption_geolocation": [
          49.00888888888889,
          8.439444444444444
        ]
      },
      "paper_deviation": "AutoTS error differs from paper 2.15 m; ablation error differs from paper 3.39 m",
      "location_points": [
        {
          "index": 0,
          "frame_id": "2011_09_26_drive_0009_0000000127",
          "lat": 49.008863501489394,
          "lon": 8.439587991239714,
          "is_outlier": false
        },
        {
          "index": 1,
          "frame_id": "2011_09_26_drive_0009_0000000131",
          "lat": 49.00887190198476,
          "lon": 8.439548017058002,
          "is_outlier": false
        },
        {
          "index": 2,
          "frame_id": "2011_09_26_drive_0009_0000000133",
          "lat": 49.00887547547555,
          "lon": 8.43952759723983,
          "is_outlier": false
        },
        {
          "index": 3,
          "frame_id": "2011_09_26_drive_0009_0000000135",
          "lat": 49.00887561011504,
          "lon": 8.439521390943309,
          "is_outlier": false
        },
        {
          "index": 4,
          "frame_id": "2011_09_26_drive_0009_0000000137",
          "lat": 49.00887597497707,
          "lon": 8.439515557817826,
          "is_outlier": false
        },
        {
          "index": 5,
          "frame_id": "2011_09_26_drive_0009_0000000139",
          "lat": 49.008877500080025,
          "lon": 8.439507297015917,
          "is_outlier": false
        },
        {
          "index": 6,
          "frame_id": "2011_09_26_drive_0009_0000000141",
          "lat": 49.008882112627425,
          "lon": 8.439485801413536,
          "is_outlier": false
        },
        {
          "index": 7,
          "frame_id": "2011_09_26_drive_0009_0000000143",
          "lat": 49.008882033423625,
          "lon": 8.439484172035506,
          "is_outlier": false
        },
        {
          "index": 8,
          "frame_id": "2011_09_26_drive_0009_0000000145",
          "lat": 49.008877368374534,
          "lon": 8.439498044359532,
          "is_outlier": false
        },
        {
          "index": 9,
          "frame_id": "2011_09_26_drive_0009_0000000147",
          "lat": 49.00887572701284,
          "lon": 8.439499165266628,
          "is_outlier": false
        },
        {
          "index": 10,
          "frame_id": "2011_09_26_drive_0009_0000000149",
          "lat": 49.00887895165025,
          "lon": 8.439487179089255,
          "is_outlier": false
        },
        {
          "index": 11,
          "frame_id": "2011_09_26_drive_0009_0000000151",
          "lat": 49.00887903183521,
          "lon": 8.43948418327876,
          "is_outlier": false
        },
        {
          "index": 12,
          "frame_id": "2011_09_26_drive_0009_0000000153",
          "lat": 49.008881402657686,
          "lon": 8.439474680445892,
          "is_outlier": false
        },
        {
          "index": 13,
          "frame_id": "2011_09_26_drive_0009_0000000155",
          "lat": 49.00888040011079,
          "lon": 8.439474110734785,
          "is_outlier": false
        }
      ],
      "gt_location_points": [
        {
          "index": 0,
          "frame_id": "2011_09_26_drive_0009_0000000125",
          "lat": 49.00886250143705,
          "lon": 8.439593353693628
        },
        {
          "index": 1,
          "frame_id": "2011_09_26_drive_0009_0000000127",
          "lat": 49.008862969544424,
          "lon": 8.439587593518944
        },
        {
          "index": 2,
          "frame_id": "2011_09_26_drive_0009_0000000129",
          "lat": 49.008869045016894,
          "lon": 8.43955966857098
        },
        {
          "index": 3,
          "frame_id": "2011_09_26_drive_0009_0000000131",
          "lat": 49.0088717716288,
          "lon": 8.439545228727606
        },
        {
          "index": 4,
          "frame_id": "2011_09_26_drive_0009_0000000133",
          "lat": 49.008875615415334,
          "lon": 8.439525788080715
        },
        {
          "index": 5,
          "frame_id": "2011_09_26_drive_0009_0000000135",
          "lat": 49.00887596110218,
          "lon": 8.439520007232085
        },
        {
          "index": 6,
          "frame_id": "2011_09_26_drive_0009_0000000137",
          "lat": 49.00887581572748,
          "lon": 8.439515885202294
        },
        {
          "index": 7,
          "frame_id": "2011_09_26_drive_0009_0000000139",
          "lat": 49.008876991482715,
          "lon": 8.439508566465854
        },
        {
          "index": 8,
          "frame_id": "2011_09_26_drive_0009_0000000141",
          "lat": 49.00888225468568,
          "lon": 8.43948526466026
        },
        {
          "index": 9,
          "frame_id": "2011_09_26_drive_0009_0000000143",
          "lat": 49.00888168056709,
          "lon": 8.439484346074806
        },
        {
          "index": 10,
          "frame_id": "2011_09_26_drive_0009_0000000145",
          "lat": 49.00887724071728,
          "lon": 8.439497071721554
        },
        {
          "index": 11,
          "frame_id": "2011_09_26_drive_0009_0000000147",
          "lat": 49.00887610537676,
          "lon": 8.439497821633852
        },
        {
          "index": 12,
          "frame_id": "2011_09_26_drive_0009_0000000149",
          "lat": 49.00887892737683,
          "lon": 8.439486716958877
        },
        {
          "index": 13,
          "frame_id": "2011_09_26_drive_0009_0000000151",
          "lat": 49.00887895793143,
          "lon": 8.439484402593404
        },
        {
          "index": 14,
          "frame_id": "2011_09_26_drive_0009_0000000153",
          "lat": 49.008881105338446,
          "lon": 8.439475278413036
        },
        {
          "index": 15,
          "frame_id": "2011_09_26_drive_0009_0000000155",
          "lat": 49.008880087016614,
          "lon": 8.439474789845216
        }
      ],
      "frames": [
        {
          "frame_id": "2011_09_26_drive_0009_0000000125",
          "image_src": "KITTI-TS/train_img/2011_09_26_drive_0009_0000000125.png",
          "image_size": [
            1242,
            375
          ],
          "camera_gps": [
            49.008999057076,
            8.4389850044288
          ],
          "gt_box": [
            660.0,
            146.0,
            677.0,
            163.0
          ],
          "detected_box": null,
          "detected_score": null,
          "detected_location_point": null,
          "gt_location_point": [
            49.00886250143705,
            8.439593353693628
          ]
        },
        {
          "frame_id": "2011_09_26_drive_0009_0000000127",
          "image_src": "KITTI-TS/train_img/2011_09_26_drive_0009_0000000127.png",
          "image_size": [
            1242,
            375
          ],
          "camera_gps": [
            49.008994139427,
            8.4390125101702
          ],
          "gt_box": [
            663.0,
            144.0,
            682.0,
            163.0
          ],
          "detected_box": [
            661.0516357421875,
            141.91314697265625,
            681.6253662109375,
            162.72772216796875
          ],
          "detected_score": 0.07042032480239868,
          "detected_location_point": [
            49.008863501489394,
            8.439587991239714
          ],
          "gt_location_point": [
            49.008862969544424,
            8.439587593518944
          ]
        },
        {
          "frame_id": "2011_09_26_drive_0009_0000000129",
          "image_src": "KITTI-TS/train_img/2011_09_26_drive_0009_0000000129.png",
          "image_size": [
            1242,
            375
          ],
          "camera_gps": [
            49.008988979024,
            8.4390411180066
          ],
          "gt_box": [
            666.0,
            140.0,
            685.0,
            161.0
          ],
          "detected_box": null,
          "detected_score": null,
          "detected_location_point": null,
          "gt_location_point": [
            49.008869045016894,
            8.43955966857098
          ]
        },
        {
          "frame_id": "2011_09_26_drive_0009_0000000131",
          "image_src": "KITTI-TS/train_img/2011_09_26_drive_0009_0000000131.png",
          "image_size": [
            1242,
            375
          ],
          "camera_gps": [
            49.008983897017,
            8.4390694039641
          ],
          "gt_box": [
            669.0,
            139.0,
            690.0,
            160.0
          ],
          "detected_box": [
            666.0516357421875,
            136.24839782714844,
            689.4404907226562,
            159.92105102539062
          ],
          "detected_score": 0.9860026836395264,
          "detected_location_point": [
            49.00887190198476,
            8.439548017058002
          ],
          "gt_location_point": [
            49.0088717716288,
            8.439545228727606
          ]
        },
        {
          "frame_id": "2011_09_26_drive_0009_0000000133",
          "image_src": "KITTI-TS/train_img/2011_09_26_drive_0009_0000000133.png",
          "image_size": [
            1242,
            375
          ],
          "camera_gps": [
            49.008978942181,
            8.439095717802
          ],
          "gt_box": [
            673.0,
            142.0,
            694.0,
            163.0
          ],
          "detected_box": [
            671.1696166992188,
            139.63711547851562,
            694.3825073242188,
            163.43006896972656
          ],
          "detected_score": 0.9952937960624695,
          "detected_location_point": [
            49.00887547547555,
            8.43952759723983
          ],
          "gt_location_point": [
            49.008875615415334,
            8.439525788080715
          ]
        },
        {
          "frame_id": "2011_09_26_drive_0009_0000000135",
          "image_src": "KITTI-TS/train_img/2011_09_26_drive_0009_0000000135.png",
          "image_size": [
            1242,
            375
          ],
          "camera_gps": [
            49.008973672175,
            8.4391230848208
          ],
          "gt_box": [
            677.0,
            143.0,
            701.0,
            167.0
          ],
          "detected_box": [
            676.19873046875,
            142.05673217773438,
            701.8560791015625,
            166.5150604248047
          ],
          "detected_score": 0.9971697926521301,
          "detected_location_point": [
            49.00887561011504,
            8.439521390943309
          ],
          "gt_location_point": [
            49.00887596110218,
            8.439520007232085
          ]
        },
        {
          "frame_id": "2011_09_26_drive_0009_0000000137",
          "image_src": "KITTI-TS/train_img/2011_09_26_drive_0009_0000000137.png",
          "image_size": [
            1242,
            375
          ],
          "camera_gps": [
            49.008968535543,
            8.4391502463928
          ],
          "gt_box": [
            681.0,
            140.0,
            710.0,
            166.0
          ],
          "detected_box": [
            680.35546875,
            138.76988220214844,
            710.207763671875,
            165.0926971435547
          ],
          "detected_score": 0.9978559613227844,
          "detected_location_point": [
            49.00887597497707,
            8.439515557817826
          ],
          "gt_location_point": [
            49.00887581572748,
            8.439515885202294
          ]
        },
        {
          "frame_id": "2011_09_26_drive_0009_0000000139",
          "image_src": "KITTI-TS/train_img/2011_09_26_drive_0009_0000000139.png",
          "image_size": [
            1242,
            375
          ],
          "camera_gps": [
            49.008963466526,
            8.4391771401523
          ],
          "gt_box": [
            686.0,
            134.0,
            716.0,
            163.0
          ],
          "detected_box": [
            686.3560791015625,
            133.2280731201172,
            714.5277099609375,
            161.131591796875
          ],
          "detected_score": 0.9979546070098877,
          "detected_location_point": [
            49.008877500080025,
            8.439507297015917
          ],
          "gt_location_point": [
            49.008876991482715,
            8.439508566465854
          ]
        },
        {
          "frame_id": "2011_09_26_drive_0009_0000000141",
          "image_src": "KITTI-TS/train_img/2011_09_26_drive_0009_0000000141.png",
          "image_size": [
            1242,
            375
          ],
          "camera_gps": [
            49.008958680049,
            8.4392023268674
          ],
          "gt_box": [
            692.0,
            134.0,
            723.0,
            164.0
          ],
          "detected_box": [
            691.2553100585938,
            132.89599609375,
            723.7234497070312,
            162.73988342285156
          ],
          "detected_score": 0.9972414970397949,
          "detected_location_point": [
            49.008882112627425,
            8.439485801413536
          ],
          "gt_location_point": [
            49.00888225468568,
            8.43948526466026
          ]
        },
        {
          "frame_id": "2011_09_26_drive_0009_0000000143",
          "image_src": "KITTI-TS/train_img/2011_09_26_drive_0009_0000000143.png",
          "image_size": [
            1242,
            375
          ],
          "camera_gps": [
            49.008953705834,
            8.4392281514298
          ],
          "gt_box": [
            697.0,
            132.0,
            734.0,
            165.0
          ],
          "detected_box": [
            696.3341064453125,
            131.25662231445312,
            732.2513427734375,
            163.7018280029297
          ],
          "detected_score": 0.998024582862854,
          "detected_location_point": [
            49.008882033423625,
            8.439484172035506
          ],
          "gt_location_point": [
            49.00888168056709,
            8.439484346074806
          ]
        },
        {
          "frame_id": "2011_09_26_drive_0009_0000000145",
          "image_src": "KITTI-TS/train_img/2011_09_26_drive_0009_0000000145.png",
          "image_size": [
            1242,
            375
          ],
          "camera_gps": [
            49.008948793447,
            8.4392532371137
          ],
          "gt_box": [
            706.0,
            125.0,
            744.0,
            161.0
          ],
          "detected_box": [
            703.9866333007812,
            124.57545471191406,
            742.6271362304688,
            160.05587768554688
          ],
          "detected_score": 0.9983009696006775,
          "detected_location_point": [
            49.008877368374534,
            8.439498044359532
          ],
          "gt_location_point": [
            49.00887724071728,
            8.439497071721554
          ]
        },
        {
          "frame_id": "2011_09_26_drive_0009_0000000147",
          "image_src": "KITTI-TS/train_img/2011_09_26_drive_0009_0000000147.png",
          "image_size": [
            1242,
            375
          ],
          "camera_gps": [
            49.008944189441,
            8.4392764073311
          ],
          "gt_box": [
            714.0,
            116.0,
            758.0,
            155.0
          ],
          "detected_box": [
            713.2442626953125,
            115.02645111083984,
            758.447509765625,
            155.2128448486328
          ],
          "detected_score": 0.9982535243034363,
          "detected_location_point": [
            49.00887572701284,
            8.439499165266628
          ],
          "gt_location_point": [
            49.00887610537676,
            8.439497821633852
          ]
        },
        {
          "frame_id": "2011_09_26_drive_0009_0000000149",
          "image_src": "KITTI-TS/train_img/2011_09_26_drive_0009_0000000149.png",
          "image_size": [
            1242,
            375
          ],
          "camera_gps": [
            49.00893945761,
            8.4392999420211
          ],
          "gt_box": [
            724.0,
            108.0,
            774.0,
            151.0
          ],
          "detected_box": [
            722.9760131835938,
            106.7988510131836,
            773.2249145507812,
            150.85220336914062
          ],
          "detected_score": 0.9982258677482605,
          "detected_location_point": [
            49.00887895165025,
            8.439487179089255
          ],
          "gt_location_point": [
            49.00887892737683,
            8.439486716958877
          ]
        },
        {
          "frame_id": "2011_09_26_drive_0009_0000000151",
          "image_src": "KITTI-TS/train_img/2011_09_26_drive_0009_0000000151.png",
          "image_size": [
            1242,
            375
          ],
          "camera_gps": [
            49.008934862271,
            8.439322670656
          ],
          "gt_box": [
            740.0,
            100.0,
            794.0,
            151.0
          ],
          "detected_box": [
            740.6255493164062,
            100.18247985839844,
            793.3966674804688,
            150.20997619628906
          ],
          "detected_score": 0.9978391528129578,
          "detected_location_point": [
            49.00887903183521,
            8.43948418327876
          ],
          "gt_location_point": [
            49.00887895793143,
            8.439484402593404
          ]
        },
        {
          "frame_id": "2011_09_26_drive_0009_0000000153",
          "image_src": "KITTI-TS/train_img/2011_09_26_drive_0009_0000000153.png",
          "image_size": [
            1242,
            375
          ],
          "camera_gps": [
            49.008930397556,
            8.4393445238329
          ],
          "gt_box": [
            760.0,
            90.0,
            827.0,
            150.0
          ],
          "detected_box": [
            759.5634765625,
            90.04350280761719,
            826.4365844726562,
            148.51998901367188
          ],
          "detected_score": 0.9964744448661804,
          "detected_location_point": [
            49.008881402657686,
            8.439474680445892
          ],
          "gt_location_point": [
            49.008881105338446,
            8.439475278413036
          ]
        },
        {
          "frame_id": "2011_09_26_drive_0009_0000000155",
          "image_src": "KITTI-TS/train_img/2011_09_26_drive_0009_0000000155.png",
          "image_size": [
            1242,
            375
          ],
          "camera_gps": [
            49.008926247386,
            8.4393644513731
          ],
          "gt_box": [
            788.0,
            73.0,
            869.0,
            146.0
          ],
          "detected_box": [
            787.8339233398438,
            73.32515716552734,
            868.7135620117188,
            145.4659423828125
          ],
          "detected_score": 0.9954463839530945,
          "detected_location_point": [
            49.00888040011079,
            8.439474110734785
          ],
          "gt_location_point": [
            49.008880087016614,
            8.439474789845216
          ]
        }
      ]
    },
    {
      "index": 2,
      "split": "train",
      "sign_id": "274",
      "selection_reason": "paper specified sample",
      "matches_paper_sample": true,
      "category": 3,
      "paper_label": "RoadWork",
      "gt_direction": 1,
      "gt_direction_name": "Backward",
      "pred_direction": 1,
      "pred_direction_name": "Backward",
      "ablation": "AutoTS w/o MinCut",
      "gt_location": [
        48.949110515613015,
        8.488704282180446
      ],
      "autots": {
        "pred": [
          48.949119122916954,
          8.488695333033089
        ],
        "error_m": 1.1601361912196417,
        "outlier_indices": []
      },
      "ablation_result": {
        "pred": [
          48.949119122916954,
          8.488695333033089
        ],
        "error_m": 1.1601361912196417
      },
      "paper_reference": {
        "sign_label": "RoadWork",
        "gt_direction": 1,
        "gt_direction_name": "Backward",
        "pred_direction": 1,
        "pred_direction_name": "Backward",
        "autots_error_m": 1.57,
        "ablation_error_m": 1.57,
        "caption_geolocation": [
          48.94911111111111,
          8.488694444444443
        ]
      },
      "paper_deviation": "AutoTS error differs from paper 1.57 m; ablation error differs from paper 1.57 m",
      "location_points": [
        {
          "index": 0,
          "frame_id": "2011_10_03_drive_0047_0000000270",
          "lat": 48.94912112978915,
          "lon": 8.488694721262593,
          "is_outlier": false
        },
        {
          "index": 1,
          "frame_id": "2011_10_03_drive_0047_0000000271",
          "lat": 48.949119979991956,
          "lon": 8.488695442842808,
          "is_outlier": false
        },
        {
          "index": 2,
          "frame_id": "2011_10_03_drive_0047_0000000272",
          "lat": 48.94911360689898,
          "lon": 8.488702451624732,
          "is_outlier": false
        },
        {
          "index": 3,
          "frame_id": "2011_10_03_drive_0047_0000000273",
          "lat": 48.94911823893119,
          "lon": 8.488696941789199,
          "is_outlier": false
        },
        {
          "index": 4,
          "frame_id": "2011_10_03_drive_0047_0000000274",
          "lat": 48.94911815187047,
          "lon": 8.488696948787428,
          "is_outlier": false
        },
        {
          "index": 5,
          "frame_id": "2011_10_03_drive_0047_0000000275",
          "lat": 48.94911367953648,
          "lon": 8.488701252108157,
          "is_outlier": false
        },
        {
          "index": 6,
          "frame_id": "2011_10_03_drive_0047_0000000276",
          "lat": 48.94911373108666,
          "lon": 8.488701133258632,
          "is_outlier": false
        },
        {
          "index": 7,
          "frame_id": "2011_10_03_drive_0047_0000000277",
          "lat": 48.94911163669496,
          "lon": 8.488703085275693,
          "is_outlier": false
        },
        {
          "index": 8,
          "frame_id": "2011_10_03_drive_0047_0000000278",
          "lat": 48.949121737945354,
          "lon": 8.488692199641578,
          "is_outlier": false
        },
        {
          "index": 9,
          "frame_id": "2011_10_03_drive_0047_0000000279",
          "lat": 48.94911624640198,
          "lon": 8.488697318187597,
          "is_outlier": false
        },
        {
          "index": 10,
          "frame_id": "2011_10_03_drive_0047_0000000280",
          "lat": 48.9491187461124,
          "lon": 8.488695009303724,
          "is_outlier": false
        },
        {
          "index": 11,
          "frame_id": "2011_10_03_drive_0047_0000000281",
          "lat": 48.94912530972231,
          "lon": 8.48868836471026,
          "is_outlier": false
        },
        {
          "index": 12,
          "frame_id": "2011_10_03_drive_0047_0000000282",
          "lat": 48.94912579412997,
          "lon": 8.488687781999925,
          "is_outlier": false
        },
        {
          "index": 13,
          "frame_id": "2011_10_03_drive_0047_0000000283",
          "lat": 48.94912101870659,
          "lon": 8.48869265808609,
          "is_outlier": false
        },
        {
          "index": 14,
          "frame_id": "2011_10_03_drive_0047_0000000284",
          "lat": 48.94912578345569,
          "lon": 8.488687988357476,
          "is_outlier": false
        },
        {
          "index": 15,
          "frame_id": "2011_10_03_drive_0047_0000000285",
          "lat": 48.94911948841602,
          "lon": 8.488694436103497,
          "is_outlier": false
        },
        {
          "index": 16,
          "frame_id": "2011_10_03_drive_0047_0000000286",
          "lat": 48.94912067517914,
          "lon": 8.488693024162938,
          "is_outlier": false
        }
      ],
      "gt_location_points": [
        {
          "index": 0,
          "frame_id": "2011_10_03_drive_0047_0000000270",
          "lat": 48.94912589124197,
          "lon": 8.488688934957006
        },
        {
          "index": 1,
          "frame_id": "2011_10_03_drive_0047_0000000271",
          "lat": 48.949121030888094,
          "lon": 8.488693857621987
        },
        {
          "index": 2,
          "frame_id": "2011_10_03_drive_0047_0000000272",
          "lat": 48.94911420219351,
          "lon": 8.488701608200717
        },
        {
          "index": 3,
          "frame_id": "2011_10_03_drive_0047_0000000273",
          "lat": 48.949119633046685,
          "lon": 8.488695197101755
        },
        {
          "index": 4,
          "frame_id": "2011_10_03_drive_0047_0000000274",
          "lat": 48.94912209229372,
          "lon": 8.488692358388683
        },
        {
          "index": 5,
          "frame_id": "2011_10_03_drive_0047_0000000275",
          "lat": 48.9491188940217,
          "lon": 8.488695159106799
        },
        {
          "index": 6,
          "frame_id": "2011_10_03_drive_0047_0000000276",
          "lat": 48.949117329349214,
          "lon": 8.488697010386149
        },
        {
          "index": 7,
          "frame_id": "2011_10_03_drive_0047_0000000277",
          "lat": 48.949119330238375,
          "lon": 8.488694620904642
        },
        {
          "index": 8,
          "frame_id": "2011_10_03_drive_0047_0000000278",
          "lat": 48.94912403044974,
          "lon": 8.488689570068281
        },
        {
          "index": 9,
          "frame_id": "2011_10_03_drive_0047_0000000279",
          "lat": 48.9491173782686,
          "lon": 8.488695849510577
        },
        {
          "index": 10,
          "frame_id": "2011_10_03_drive_0047_0000000280",
          "lat": 48.94912263134152,
          "lon": 8.488690719010126
        },
        {
          "index": 11,
          "frame_id": "2011_10_03_drive_0047_0000000281",
          "lat": 48.94912790086606,
          "lon": 8.488685480601294
        },
        {
          "index": 12,
          "frame_id": "2011_10_03_drive_0047_0000000282",
          "lat": 48.94912958422987,
          "lon": 8.488683689653055
        },
        {
          "index": 13,
          "frame_id": "2011_10_03_drive_0047_0000000283",
          "lat": 48.94912383288367,
          "lon": 8.488689529319467
        },
        {
          "index": 14,
          "frame_id": "2011_10_03_drive_0047_0000000284",
          "lat": 48.949125819618374,
          "lon": 8.488687656209176
        },
        {
          "index": 15,
          "frame_id": "2011_10_03_drive_0047_0000000285",
          "lat": 48.949120749085985,
          "lon": 8.48869294231018
        },
        {
          "index": 16,
          "frame_id": "2011_10_03_drive_0047_0000000286",
          "lat": 48.94912071720953,
          "lon": 8.48869276218195
        }
      ],
      "frames": [
        {
          "frame_id": "2011_10_03_drive_0047_0000000270",
          "image_src": "KITTI-TS/train_img/2011_10_03_drive_0047_0000000270.png",
          "image_size": [
            1241,
            376
          ],
          "camera_gps": [
            48.949286855088,
            8.488508026904
          ],
          "gt_box": [
            645.0,
            132.0,
            684.0,
            168.0
          ],
          "detected_box": [
            643.992431640625,
            130.7931671142578,
            683.2432861328125,
            167.42605590820312
          ],
          "detected_score": 0.9737759828567505,
          "detected_location_point": [
            48.94912112978915,
            8.488694721262593
          ],
          "gt_location_point": [
            48.94912589124197,
            8.488688934957006
          ]
        },
        {
          "frame_id": "2011_10_03_drive_0047_0000000271",
          "image_src": "KITTI-TS/train_img/2011_10_03_drive_0047_0000000271.png",
          "image_size": [
            1241,
            376
          ],
          "camera_gps": [
            48.949280613255,
            8.4885158746751
          ],
          "gt_box": [
            647.0,
            131.0,
            688.0,
            171.0
          ],
          "detected_box": [
            645.2967529296875,
            128.86331176757812,
            687.9646606445312,
            169.8385009765625
          ],
          "detected_score": 0.9868890047073364,
          "detected_location_point": [
            48.949119979991956,
            8.488695442842808
          ],
          "gt_location_point": [
            48.949121030888094,
            8.488693857621987
          ]
        },
        {
          "frame_id": "2011_10_03_drive_0047_0000000272",
          "image_src": "KITTI-TS/train_img/2011_10_03_drive_0047_0000000272.png",
          "image_size": [
            1241,
            376
          ],
          "camera_gps": [
            48.949273787181,
            8.4885244972905
          ],
          "gt_box": [
            648.0,
            130.0,
            691.0,
            170.0
          ],
          "detected_box": [
            647.2100830078125,
            128.39349365234375,
            691.0156860351562,
            169.29150390625
          ],
          "detected_score": 0.9707725644111633,
          "detected_location_point": [
            48.94911360689898,
            8.488702451624732
          ],
          "gt_location_point": [
            48.94911420219351,
            8.488701608200717
          ]
        },
        {
          "frame_id": "2011_10_03_drive_0047_0000000273",
          "image_src": "KITTI-TS/train_img/2011_10_03_drive_0047_0000000273.png",
          "image_size": [
            1241,
            376
          ],
          "camera_gps": [
            48.949267583939,
            8.4885323085296
          ],
          "gt_box": [
            651.0,
            127.0,
            694.0,
            170.0
          ],
          "detected_box": [
            649.5763549804688,
            125.19428253173828,
            694.4650268554688,
            168.80226135253906
          ],
          "detected_score": 0.9828064441680908,
          "detected_location_point": [
            48.94911823893119,
            8.488696941789199
          ],
          "gt_location_point": [
            48.949119633046685,
            8.488695197101755
          ]
        },
        {
          "frame_id": "2011_10_03_drive_0047_0000000274",
          "image_src": "KITTI-TS/train_img/2011_10_03_drive_0047_0000000274.png",
          "image_size": [
            1241,
            376
          ],
          "camera_gps": [
            48.949260794878,
            8.4885408858893
          ],
          "gt_box": [
            652.0,
            126.0,
            699.0,
            169.0
          ],
          "detected_box": [
            650.796875,
            124.85380554199219,
            698.8218994140625,
            168.1556396484375
          ],
          "detected_score": 0.9854208827018738,
          "detected_location_point": [
            48.94911815187047,
            8.488696948787428
          ],
          "gt_location_point": [
            48.94912209229372,
            8.488692358388683
          ]
        },
        {
          "frame_id": "2011_10_03_drive_0047_0000000275",
          "image_src": "KITTI-TS/train_img/2011_10_03_drive_0047_0000000275.png",
          "image_size": [
            1241,
            376
          ],
          "camera_gps": [
            48.949254652276,
            8.4885486735328
          ],
          "gt_box": [
            655.0,
            123.0,
            705.0,
            167.0
          ],
          "detected_box": [
            653.6089477539062,
            121.94032287597656,
            704.1033935546875,
            165.57855224609375
          ],
          "detected_score": 0.9734566807746887,
          "detected_location_point": [
            48.94911367953648,
            8.488701252108157
          ],
          "gt_location_point": [
            48.9491188940217,
            8.488695159106799
          ]
        },
        {
          "frame_id": "2011_10_03_drive_0047_0000000276",
          "image_src": "KITTI-TS/train_img/2011_10_03_drive_0047_0000000276.png",
          "image_size": [
            1241,
            376
          ],
          "camera_gps": [
            48.949248551775,
            8.4885564349843
          ],
          "gt_box": [
            659.0,
            120.0,
            707.0,
            166.0
          ],
          "detected_box": [
            657.3971557617188,
            118.07254028320312,
            707.2206420898438,
            164.75267028808594
          ],
          "detected_score": 0.9540119767189026,
          "detected_location_point": [
            48.94911373108666,
            8.488701133258632
          ],
          "gt_location_point": [
            48.949117329349214,
            8.488697010386149
          ]
        },
        {
          "frame_id": "2011_10_03_drive_0047_0000000277",
          "image_src": "KITTI-TS/train_img/2011_10_03_drive_0047_0000000277.png",
          "image_size": [
            1241,
            376
          ],
          "camera_gps": [
            48.949241860917,
            8.4885649053604
          ],
          "gt_box": [
            661.0,
            115.0,
            714.0,
            165.0
          ],
          "detected_box": [
            659.4783935546875,
            112.92623138427734,
            713.80224609375,
            163.9535369873047
          ],
          "detected_score": 0.990124523639679,
          "detected_location_point": [
            48.94911163669496,
            8.488703085275693
          ],
          "gt_location_point": [
            48.949119330238375,
            8.488694620904642
          ]
        },
        {
          "frame_id": "2011_10_03_drive_0047_0000000278",
          "image_src": "KITTI-TS/train_img/2011_10_03_drive_0047_0000000278.png",
          "image_size": [
            1241,
            376
          ],
          "camera_gps": [
            48.949235853026,
            8.488572541742
          ],
          "gt_box": [
            664.0,
            113.0,
            720.0,
            162.0
          ],
          "detected_box": [
            662.94482421875,
            110.4011459350586,
            719.6307983398438,
            161.9010772705078
          ],
          "detected_score": 0.9853543043136597,
          "detected_location_point": [
            48.949121737945354,
            8.488692199641578
          ],
          "gt_location_point": [
            48.94912403044974,
            8.488689570068281
          ]
        },
        {
          "frame_id": "2011_10_03_drive_0047_0000000279",
          "image_src": "KITTI-TS/train_img/2011_10_03_drive_0047_0000000279.png",
          "image_size": [
            1241,
            376
          ],
          "camera_gps": [
            48.949229894788,
            8.4885800986307
          ],
          "gt_box": [
            668.0,
            110.0,
            729.0,
            162.0
          ],
          "detected_box": [
            666.8919677734375,
            108.1474380493164,
            728.1984252929688,
            161.54132080078125
          ],
          "detected_score": 0.980474591255188,
          "detected_location_point": [
            48.94911624640198,
            8.488697318187597
          ],
          "gt_location_point": [
            48.9491173782686,
            8.488695849510577
          ]
        },
        {
          "frame_id": "2011_10_03_drive_0047_0000000280",
          "image_src": "KITTI-TS/train_img/2011_10_03_drive_0047_0000000280.png",
          "image_size": [
            1241,
            376
          ],
          "camera_gps": [
            48.94922340569,
            8.4885883592389
          ],
          "gt_box": [
            674.0,
            107.0,
            733.0,
            160.0
          ],
          "detected_box": [
            671.4700927734375,
            104.0347900390625,
            733.1676635742188,
            159.45550537109375
          ],
          "detected_score": 0.9880453944206238,
          "detected_location_point": [
            48.9491187461124,
            8.488695009303724
          ],
          "gt_location_point": [
            48.94912263134152,
            8.488690719010126
          ]
        },
        {
          "frame_id": "2011_10_03_drive_0047_0000000281",
          "image_src": "KITTI-TS/train_img/2011_10_03_drive_0047_0000000281.png",
          "image_size": [
            1241,
            376
          ],
          "camera_gps": [
            48.949217535553,
            8.4885958234282
          ],
          "gt_box": [
            676.0,
            101.0,
            743.0,
            162.0
          ],
          "detected_box": [
            674.351318359375,
            100.26409149169922,
            742.3487548828125,
            161.9430694580078
          ],
          "detected_score": 0.9790792465209961,
          "detected_location_point": [
            48.94912530972231,
            8.48868836471026
          ],
          "gt_location_point": [
            48.94912790086606,
            8.488685480601294
          ]
        },
        {
          "frame_id": "2011_10_03_drive_0047_0000000282",
          "image_src": "KITTI-TS/train_img/2011_10_03_drive_0047_0000000282.png",
          "image_size": [
            1241,
            376
          ],
          "camera_gps": [
            48.94921169433,
            8.4886032601852
          ],
          "gt_box": [
            684.0,
            98.0,
            751.0,
            162.0
          ],
          "detected_box": [
            681.7084350585938,
            95.96004486083984,
            750.0439453125,
            161.14125061035156
          ],
          "detected_score": 0.9866450428962708,
          "detected_location_point": [
            48.94912579412997,
            8.488687781999925
          ],
          "gt_location_point": [
            48.94912958422987,
            8.488683689653055
          ]
        },
        {
          "frame_id": "2011_10_03_drive_0047_0000000283",
          "image_src": "KITTI-TS/train_img/2011_10_03_drive_0047_0000000283.png",
          "image_size": [
            1241,
            376
          ],
          "camera_gps": [
            48.94920530753,
            8.4886113960511
          ],
          "gt_box": [
            688.0,
            95.0,
            763.0,
            160.0
          ],
          "detected_box": [
            685.7867431640625,
            92.69832611083984,
            761.4207763671875,
            158.99644470214844
          ],
          "detected_score": 0.9882937669754028,
          "detected_location_point": [
            48.94912101870659,
            8.48869265808609
          ],
          "gt_location_point": [
            48.94912383288367,
            8.488689529319467
          ]
        },
        {
          "frame_id": "2011_10_03_drive_0047_0000000284",
          "image_src": "KITTI-TS/train_img/2011_10_03_drive_0047_0000000284.png",
          "image_size": [
            1241,
            376
          ],
          "camera_gps": [
            48.949199527271,
            8.4886187428198
          ],
          "gt_box": [
            698.0,
            89.0,
            772.0,
            161.0
          ],
          "detected_box": [
            694.837890625,
            86.5452651977539,
            772.110595703125,
            159.9706268310547
          ],
          "detected_score": 0.9847992658615112,
          "detected_location_point": [
            48.94912578345569,
            8.488687988357476
          ],
          "gt_location_point": [
            48.949125819618374,
            8.488687656209176
          ]
        },
        {
          "frame_id": "2011_10_03_drive_0047_0000000285",
          "image_src": "KITTI-TS/train_img/2011_10_03_drive_0047_0000000285.png",
          "image_size": [
            1241,
            376
          ],
          "camera_gps": [
            48.949193220933,
            8.4886267732614
          ],
          "gt_box": [
            700.0,
            83.0,
            788.0,
            159.0
          ],
          "detected_box": [
            697.9230346679688,
            81.17173767089844,
            786.5258178710938,
            159.352783203125
          ],
          "detected_score": 0.9621931910514832,
          "detected_location_point": [
            48.94911948841602,
            8.488694436103497
          ],
          "gt_location_point": [
            48.949120749085985,
            8.48869294231018
          ]
        },
        {
          "frame_id": "2011_10_03_drive_0047_0000000286",
          "image_src": "KITTI-TS/train_img/2011_10_03_drive_0047_0000000286.png",
          "image_size": [
            1241,
            376
          ],
          "camera_gps": [
            48.949187535026,
            8.4886340243822
          ],
          "gt_box": [
            710.0,
            76.0,
            805.0,
            159.0
          ],
          "detected_box": [
            709.1995239257812,
            73.66006469726562,
            803.1775512695312,
            158.8423614501953
          ],
          "detected_score": 0.953219473361969,
          "detected_location_point": [
            48.94912067517914,
            8.488693024162938
          ],
          "gt_location_point": [
            48.94912071720953,
            8.48869276218195
          ]
        }
      ]
    },
    {
      "index": 3,
      "split": "test",
      "sign_id": "2",
      "selection_reason": "paper specified sample",
      "matches_paper_sample": true,
      "category": 4,
      "paper_label": "Yield",
      "gt_direction": 2,
      "gt_direction_name": "Rightward",
      "pred_direction": 0,
      "pred_direction_name": "Leftward",
      "ablation": "AutoTS w/o Weight",
      "gt_location": [
        49.011037071073396,
        8.423320115507977
      ],
      "autots": {
        "pred": [
          49.011038612180194,
          8.423309074505614
        ],
        "error_m": 0.8256942638657968,
        "outlier_indices": []
      },
      "ablation_result": {
        "pred": [
          49.01103860195189,
          8.42330910514452
        ],
        "error_m": 0.8232658211857367
      },
      "paper_reference": {
        "sign_label": "Yield",
        "gt_direction": 2,
        "gt_direction_name": "Rightward",
        "pred_direction": 2,
        "pred_direction_name": "Rightward",
        "autots_error_m": 0.85,
        "ablation_error_m": 1.13,
        "caption_geolocation": [
          49.010888888888886,
          8.423333333333332
        ]
      },
      "paper_deviation": "prediction differs from paper (Rightward); ablation error differs from paper 1.13 m",
      "location_points": [
        {
          "index": 0,
          "frame_id": "2011_09_26_drive_0005_0000000077",
          "lat": 49.01103615130657,
          "lon": 8.423309708835479,
          "is_outlier": false
        },
        {
          "index": 1,
          "frame_id": "2011_09_26_drive_0005_0000000078",
          "lat": 49.01103605380518,
          "lon": 8.423314411156907,
          "is_outlier": false
        },
        {
          "index": 2,
          "frame_id": "2011_09_26_drive_0005_0000000079",
          "lat": 49.01103654373195,
          "lon": 8.423315497248067,
          "is_outlier": false
        },
        {
          "index": 3,
          "frame_id": "2011_09_26_drive_0005_0000000080",
          "lat": 49.01103773195525,
          "lon": 8.423310903665879,
          "is_outlier": false
        },
        {
          "index": 4,
          "frame_id": "2011_09_26_drive_0005_0000000081",
          "lat": 49.01103932681478,
          "lon": 8.423303341050952,
          "is_outlier": false
        },
        {
          "index": 5,
          "frame_id": "2011_09_26_drive_0005_0000000082",
          "lat": 49.011039955084684,
          "lon": 8.423307217041208,
          "is_outlier": false
        },
        {
          "index": 6,
          "frame_id": "2011_09_26_drive_0005_0000000083",
          "lat": 49.01104083152367,
          "lon": 8.423305724579812,
          "is_outlier": false
        },
        {
          "index": 7,
          "frame_id": "2011_09_26_drive_0005_0000000084",
          "lat": 49.01104222139332,
          "lon": 8.423306037578705,
          "is_outlier": false
        }
      ],
      "gt_location_points": [
        {
          "index": 0,
          "frame_id": "2011_09_26_drive_0005_0000000077",
          "lat": 49.01103606627198,
          "lon": 8.423309583992523
        },
        {
          "index": 1,
          "frame_id": "2011_09_26_drive_0005_0000000078",
          "lat": 49.01103599893414,
          "lon": 8.423314276068234
        },
        {
          "index": 2,
          "frame_id": "2011_09_26_drive_0005_0000000079",
          "lat": 49.01103673647011,
          "lon": 8.423313221311162
        },
        {
          "index": 3,
          "frame_id": "2011_09_26_drive_0005_0000000080",
          "lat": 49.01103753664626,
          "lon": 8.423310750515283
        },
        {
          "index": 4,
          "frame_id": "2011_09_26_drive_0005_0000000081",
          "lat": 49.011039220622656,
          "lon": 8.42330313238867
        },
        {
          "index": 5,
          "frame_id": "2011_09_26_drive_0005_0000000082",
          "lat": 49.01103977590991,
          "lon": 8.423307050434694
        },
        {
          "index": 6,
          "frame_id": "2011_09_26_drive_0005_0000000083",
          "lat": 49.011040727379374,
          "lon": 8.423305314405438
        },
        {
          "index": 7,
          "frame_id": "2011_09_26_drive_0005_0000000084",
          "lat": 49.01104204723319,
          "lon": 8.423305751110462
        }
      ],
      "frames": [
        {
          "frame_id": "2011_09_26_drive_0005_0000000077",
          "image_src": "KITTI-TS/val2017/2011_09_26_drive_0005_0000000077.png",
          "image_size": [
            1242,
            375
          ],
          "camera_gps": [
            49.011059064177,
            8.4231671527677
          ],
          "gt_box": [
            379.0,
            87.0,
            400.0,
            143.0
          ],
          "detected_box": [
            377.5301513671875,
            86.744384765625,
            399.79632568359375,
            142.206787109375
          ],
          "detected_score": 0.7067225575447083,
          "detected_location_point": [
            49.01103615130657,
            8.423309708835479
          ],
          "gt_location_point": [
            49.01103606627198,
            8.423309583992523
          ]
        },
        {
          "frame_id": "2011_09_26_drive_0005_0000000078",
          "image_src": "KITTI-TS/val2017/2011_09_26_drive_0005_0000000078.png",
          "image_size": [
            1242,
            375
          ],
          "camera_gps": [
            49.011057714161,
            8.4231717325943
          ],
          "gt_box": [
            352.0,
            83.0,
            373.0,
            141.0
          ],
          "detected_box": [
            350.8157958984375,
            81.67839050292969,
            372.9774475097656,
            140.90237426757812
          ],
          "detected_score": 0.562868058681488,
          "detected_location_point": [
            49.01103605380518,
            8.423314411156907
          ],
          "gt_location_point": [
            49.01103599893414,
            8.423314276068234
          ]
        },
        {
          "frame_id": "2011_09_26_drive_0005_0000000079",
          "image_src": "KITTI-TS/val2017/2011_09_26_drive_0005_0000000079.png",
          "image_size": [
            1242,
            375
          ],
          "camera_gps": [
            49.011056108436,
            8.4231762120076
          ],
          "gt_box": [
            321.0,
            79.0,
            345.0,
            142.0
          ],
          "detected_box": [
            319.3630065917969,
            78.83171844482422,
            344.5072326660156,
            139.0933380126953
          ],
          "detected_score": 0.6153983473777771,
          "detected_location_point": [
            49.01103654373195,
            8.423315497248067
          ],
          "gt_location_point": [
            49.01103673647011,
            8.423313221311162
          ]
        },
        {
          "frame_id": "2011_09_26_drive_0005_0000000080",
          "image_src": "KITTI-TS/val2017/2011_09_26_drive_0005_0000000080.png",
          "image_size": [
            1242,
            375
          ],
          "camera_gps": [
            49.011054292439,
            8.42318106881
          ],
          "gt_box": [
            286.0,
            75.0,
            313.0,
            140.0
          ],
          "detected_box": [
            283.55755615234375,
            73.19086456298828,
            311.6059265136719,
            139.91407775878906
          ],
          "detected_score": 0.616166353225708,
          "detected_location_point": [
            49.01103773195525,
            8.423310903665879
          ],
          "gt_location_point": [
            49.01103753664626,
            8.423310750515283
          ]
        },
        {
          "frame_id": "2011_09_26_drive_0005_0000000081",
          "image_src": "KITTI-TS/val2017/2011_09_26_drive_0005_0000000081.png",
          "image_size": [
            1242,
            375
          ],
          "camera_gps": [
            49.011052614969,
            8.4231854443937
          ],
          "gt_box": [
            248.0,
            71.0,
            278.0,
            140.0
          ],
          "detected_box": [
            246.22032165527344,
            70.51571655273438,
            277.2064208984375,
            139.8223114013672
          ],
          "detected_score": 0.7219946980476379,
          "detected_location_point": [
            49.01103932681478,
            8.423303341050952
          ],
          "gt_location_point": [
            49.011039220622656,
            8.42330313238867
          ]
        },
        {
          "frame_id": "2011_09_26_drive_0005_0000000082",
          "image_src": "KITTI-TS/val2017/2011_09_26_drive_0005_0000000082.png",
          "image_size": [
            1242,
            375
          ],
          "camera_gps": [
            49.011050853755,
            8.423189792168
          ],
          "gt_box": [
            206.0,
            64.0,
            237.0,
            140.0
          ],
          "detected_box": [
            203.72482299804688,
            63.36146545410156,
            235.36407470703125,
            141.97727966308594
          ],
          "detected_score": 0.7013450860977173,
          "detected_location_point": [
            49.011039955084684,
            8.423307217041208
          ],
          "gt_location_point": [
            49.01103977590991,
            8.423307050434694
          ]
        },
        {
          "frame_id": "2011_09_26_drive_0005_0000000083",
          "image_src": "KITTI-TS/val2017/2011_09_26_drive_0005_0000000083.png",
          "image_size": [
            1242,
            375
          ],
          "camera_gps": [
            49.011048799306,
            8.4231945285325
          ],
          "gt_box": [
            156.0,
            59.0,
            193.0,
            138.0
          ],
          "detected_box": [
            153.45376586914062,
            57.46304702758789,
            192.68316650390625,
            139.57894897460938
          ],
          "detected_score": 0.7893764972686768,
          "detected_location_point": [
            49.01104083152367,
            8.423305724579812
          ],
          "gt_location_point": [
            49.011040727379374,
            8.423305314405438
          ]
        },
        {
          "frame_id": "2011_09_26_drive_0005_0000000084",
          "image_src": "KITTI-TS/val2017/2011_09_26_drive_0005_0000000084.png",
          "image_size": [
            1242,
            375
          ],
          "camera_gps": [
            49.011046719235,
            8.4231987892549
          ],
          "gt_box": [
            98.0,
            51.0,
            142.0,
            136.0
          ],
          "detected_box": [
            96.24581909179688,
            48.503944396972656,
            139.5875701904297,
            138.03538513183594
          ],
          "detected_score": 0.8136782646179199,
          "detected_location_point": [
            49.01104222139332,
            8.423306037578705
          ],
          "gt_location_point": [
            49.01104204723319,
            8.423305751110462
          ]
        }
      ]
    },
    {
      "index": 4,
      "split": "train",
      "sign_id": "174",
      "selection_reason": "paper specified sample",
      "matches_paper_sample": true,
      "category": 7,
      "paper_label": "NoStay",
      "gt_direction": 1,
      "gt_direction_name": "Backward",
      "pred_direction": 1,
      "pred_direction_name": "Backward",
      "ablation": "AutoTS w/o Weight",
      "gt_location": [
        48.98356159518731,
        8.401918368835496
      ],
      "autots": {
        "pred": [
          48.98355961875942,
          8.401907631644615
        ],
        "error_m": 0.8160747969064478,
        "outlier_indices": []
      },
      "ablation_result": {
        "pred": [
          48.983559688862236,
          8.401907608874724
        ],
        "error_m": 0.8156189236308168
      },
      "paper_reference": {
        "sign_label": "NoStay",
        "gt_direction": 1,
        "gt_direction_name": "Backward",
        "pred_direction": 2,
        "pred_direction_name": "Rightward",
        "autots_error_m": 0.81,
        "ablation_error_m": 0.88,
        "caption_geolocation": [
          48.983555555555554,
          8.401916666666667
        ]
      },
      "paper_deviation": "prediction differs from paper (Rightward); ablation error differs from paper 0.88 m",
      "location_points": [
        {
          "index": 0,
          "frame_id": "2011_09_30_drive_0028_0000004950",
          "lat": 48.983568021540705,
          "lon": 8.401905410621746,
          "is_outlier": false
        },
        {
          "index": 1,
          "frame_id": "2011_09_30_drive_0028_0000004951",
          "lat": 48.98356460450719,
          "lon": 8.401906505068013,
          "is_outlier": false
        },
        {
          "index": 2,
          "frame_id": "2011_09_30_drive_0028_0000004952",
          "lat": 48.983560222791034,
          "lon": 8.401907270552025,
          "is_outlier": false
        },
        {
          "index": 3,
          "frame_id": "2011_09_30_drive_0028_0000004953",
          "lat": 48.983558390100356,
          "lon": 8.401907591504985,
          "is_outlier": false
        },
        {
          "index": 4,
          "frame_id": "2011_09_30_drive_0028_0000004954",
          "lat": 48.983558726734486,
          "lon": 8.401908657284428,
          "is_outlier": false
        },
        {
          "index": 5,
          "frame_id": "2011_09_30_drive_0028_0000004955",
          "lat": 48.98355310464891,
          "lon": 8.401908469015675,
          "is_outlier": false
        },
        {
          "index": 6,
          "frame_id": "2011_09_30_drive_0028_0000004956",
          "lat": 48.983554751711715,
          "lon": 8.401909358076438,
          "is_outlier": false
        }
      ],
      "gt_location_points": [
        {
          "index": 0,
          "frame_id": "2011_09_30_drive_0028_0000004950",
          "lat": 48.98356672990505,
          "lon": 8.40190574382312
        },
        {
          "index": 1,
          "frame_id": "2011_09_30_drive_0028_0000004951",
          "lat": 48.98356456190005,
          "lon": 8.401906748353563
        },
        {
          "index": 2,
          "frame_id": "2011_09_30_drive_0028_0000004952",
          "lat": 48.98356018996589,
          "lon": 8.40190753529487
        },
        {
          "index": 3,
          "frame_id": "2011_09_30_drive_0028_0000004953",
          "lat": 48.98355813378735,
          "lon": 8.40190771762966
        },
        {
          "index": 4,
          "frame_id": "2011_09_30_drive_0028_0000004954",
          "lat": 48.98355869621958,
          "lon": 8.401908823029956
        },
        {
          "index": 5,
          "frame_id": "2011_09_30_drive_0028_0000004955",
          "lat": 48.9835530458201,
          "lon": 8.401908569409224
        },
        {
          "index": 6,
          "frame_id": "2011_09_30_drive_0028_0000004956",
          "lat": 48.98355466153346,
          "lon": 8.401909442146577
        }
      ],
      "frames": [
        {
          "frame_id": "2011_09_30_drive_0028_0000004950",
          "image_src": "KITTI-TS/train_img/2011_09_30_drive_0028_0000004950.png",
          "image_size": [
            1226,
            370
          ],
          "camera_gps": [
            48.983433373925,
            8.4019049104874
          ],
          "gt_box": [
            764.0,
            101.0,
            795.0,
            133.0
          ],
          "detected_box": [
            762.3118286132812,
            98.966064453125,
            794.0501708984375,
            132.5888671875
          ],
          "detected_score": 0.9137505888938904,
          "detected_location_point": [
            48.983568021540705,
            8.401905410621746
          ],
          "gt_location_point": [
            48.98356672990505,
            8.40190574382312
          ]
        },
        {
          "frame_id": "2011_09_30_drive_0028_0000004951",
          "image_src": "KITTI-TS/train_img/2011_09_30_drive_0028_0000004951.png",
          "image_size": [
            1226,
            370
          ],
          "camera_gps": [
            48.983443003234,
            8.4019021044781
          ],
          "gt_box": [
            784.0,
            97.0,
            819.0,
            130.0
          ],
          "detected_box": [
            782.6981201171875,
            95.85481262207031,
            818.2068481445312,
            129.42300415039062
          ],
          "detected_score": 0.9233774542808533,
          "detected_location_point": [
            48.98356460450719,
            8.401906505068013
          ],
          "gt_location_point": [
            48.98356456190005,
            8.401906748353563
          ]
        },
        {
          "frame_id": "2011_09_30_drive_0028_0000004952",
          "image_src": "KITTI-TS/train_img/2011_09_30_drive_0028_0000004952.png",
          "image_size": [
            1226,
            370
          ],
          "camera_gps": [
            48.983452620925,
            8.401899171504
          ],
          "gt_box": [
            810.0,
            89.0,
            847.0,
            126.0
          ],
          "detected_box": [
            808.30126953125,
            86.2320785522461,
            846.1197509765625,
            125.7320327758789
          ],
          "detected_score": 0.8354287147521973,
          "detected_location_point": [
            48.983560222791034,
            8.401907270552025
          ],
          "gt_location_point": [
            48.98356018996589,
            8.40190753529487
          ]
        },
        {
          "frame_id": "2011_09_30_drive_0028_0000004953",
          "image_src": "KITTI-TS/train_img/2011_09_30_drive_0028_0000004953.png",
          "image_size": [
            1226,
            370
          ],
          "camera_gps": [
            48.983463147379,
            8.4018958415002
          ],
          "gt_box": [
            839.0,
            78.0,
            882.0,
            120.0
          ],
          "detected_box": [
            837.25146484375,
            75.46720123291016,
            882.031494140625,
            120.14585876464844
          ],
          "detected_score": 0.9545813798904419,
          "detected_location_point": [
            48.983558390100356,
            8.401907591504985
          ],
          "gt_location_point": [
            48.98355813378735,
            8.40190771762966
          ]
        },
        {
          "frame_id": "2011_09_30_drive_0028_0000004954",
          "image_src": "KITTI-TS/train_img/2011_09_30_drive_0028_0000004954.png",
          "image_size": [
            1226,
            370
          ],
          "camera_gps": [
            48.983472670755,
            8.4018926227032
          ],
          "gt_box": [
            874.0,
            66.0,
            925.0,
            116.0
          ],
          "detected_box": [
            872.5742797851562,
            64.18424987792969,
            924.3826293945312,
            115.3409423828125
          ],
          "detected_score": 0.9817515015602112,
          "detected_location_point": [
            48.983558726734486,
            8.401908657284428
          ],
          "gt_location_point": [
            48.98355869621958,
            8.401908823029956
          ]
        },
        {
          "frame_id": "2011_09_30_drive_0028_0000004955",
          "image_src": "KITTI-TS/train_img/2011_09_30_drive_0028_0000004955.png",
          "image_size": [
            1226,
            370
          ],
          "camera_gps": [
            48.983482123009,
            8.4018893607678
          ],
          "gt_box": [
            918.0,
            55.0,
            977.0,
            109.0
          ],
          "detected_box": [
            916.1620483398438,
            52.54747772216797,
            977.1844482421875,
            107.61437225341797
          ],
          "detected_score": 0.9755474925041199,
          "detected_location_point": [
            48.98355310464891,
            8.401908469015675
          ],
          "gt_location_point": [
            48.9835530458201,
            8.401908569409224
          ]
        },
        {
          "frame_id": "2011_09_30_drive_0028_0000004956",
          "image_src": "KITTI-TS/train_img/2011_09_30_drive_0028_0000004956.png",
          "image_size": [
            1226,
            370
          ],
          "camera_gps": [
            48.983492466625,
            8.401885618035
          ],
          "gt_box": [
            974.0,
            37.0,
            1044.0,
            100.0
          ],
          "detected_box": [
            971.1720581054688,
            35.393924713134766,
            1044.9637451171875,
            100.02984619140625
          ],
          "detected_score": 0.9836922883987427,
          "detected_location_point": [
            48.983554751711715,
            8.401909358076438
          ],
          "gt_location_point": [
            48.98355466153346,
            8.401909442146577
          ]
        }
      ]
    }
  ]
}